trainsh/__init__.py
trainsh/__main__.py
trainsh/cli_utils.py
trainsh/config.py
trainsh/constants.py
trainsh/main.py
trainsh/requirements.txt
trainsh/commands/__init__.py
trainsh/commands/colab.py
trainsh/commands/config_cmd.py
trainsh/commands/exec_cmd.py
trainsh/commands/host.py
trainsh/commands/pricing.py
trainsh/commands/recipe.py
trainsh/commands/secrets_cmd.py
trainsh/commands/storage.py
trainsh/commands/transfer.py
trainsh/commands/update.py
trainsh/commands/vast.py
trainsh/core/__init__.py
trainsh/core/dsl_executor.py
trainsh/core/dsl_parser.py
trainsh/core/execution_log.py
trainsh/core/job_state.py
trainsh/core/models.py
trainsh/core/secrets.py
trainsh/core/tmux_session.py
trainsh/core/variables.py
trainsh/examples/aptup.recipe
trainsh/examples/brewup.recipe
trainsh/examples/hello.recipe
trainsh/examples/nanogpt-train.recipe
trainsh/examples/unsloth-finetune.recipe
trainsh/scripts/__init__.py
trainsh/services/__init__.py
trainsh/services/pricing.py
trainsh/services/recipe_executor.py
trainsh/services/sftp_browser.py
trainsh/services/ssh.py
trainsh/services/transfer_engine.py
trainsh/services/vast_api.py
trainsh/utils/__init__.py
trainsh/utils/update_checker.py
trainsh/utils/vast_formatter.py
tmux_trainsh-0.24.0.dist-info/METADATA
tmux_trainsh-0.24.0.dist-info/WHEEL
tmux_trainsh-0.24.0.dist-info/entry_points.txt
tmux_trainsh-0.24.0.dist-info/RECORD
