Metadata-Version: 2.4
Name: tmux-trainsh
Version: 0.24.0
Summary: GPU training workflow automation with tmux
License-Expression: MIT
Requires-Python: >=3.10
